FLIR/conservator/__init__.py
FLIR/conservator/config.py
FLIR/conservator/connection.py
FLIR/conservator/conservator.py
FLIR/conservator/fields_manager.py
FLIR/conservator/fields_request.py
FLIR/conservator/file_transfers.py
FLIR/conservator/local_dataset.py
FLIR/conservator/paginated_query.py
FLIR/conservator/util.py
FLIR/conservator/version.py
FLIR/conservator/cli/__init__.py
FLIR/conservator/cli/config.py
FLIR/conservator/cli/cvc.py
FLIR/conservator/cli/interactive.py
FLIR/conservator/cli/managers.py
FLIR/conservator/configs/download.json
FLIR/conservator/configs/upload.json
FLIR/conservator/generated/__init__.py
FLIR/conservator/generated/date.py
FLIR/conservator/generated/schema.py
FLIR/conservator/managers/__init__.py
FLIR/conservator/managers/media.py
FLIR/conservator/managers/searchable.py
FLIR/conservator/managers/type_manager.py
FLIR/conservator/run_tasks_plugins/conservator_cli.py
FLIR/conservator/wrappers/__init__.py
FLIR/conservator/wrappers/collection.py
FLIR/conservator/wrappers/dataset.py
FLIR/conservator/wrappers/dataset_frame.py
FLIR/conservator/wrappers/file_locker.py
FLIR/conservator/wrappers/frame.py
FLIR/conservator/wrappers/image.py
FLIR/conservator/wrappers/media.py
FLIR/conservator/wrappers/metadata.py
FLIR/conservator/wrappers/project.py
FLIR/conservator/wrappers/queryable.py
FLIR/conservator/wrappers/type_proxy.py
FLIR/conservator/wrappers/video.py
conservator_cli-2.15.1.dist-info/LICENSE
conservator_cli-2.15.1.dist-info/METADATA
conservator_cli-2.15.1.dist-info/WHEEL
conservator_cli-2.15.1.dist-info/entry_points.txt
conservator_cli-2.15.1.dist-info/top_level.txt
conservator_cli-2.15.1.dist-info/RECORD
